strato/__init__.py
strato/__main__.py
strato/version.py
strato/backends/__init__.py
strato/backends/_aws.py
strato/backends/_gcp.py
strato/backends/_local.py
strato/commands/__init__.py
strato/commands/cp.py
strato/commands/exists.py
strato/commands/rm.py
strato/commands/sync.py
strato/commands/util.py
strato/tests/helpers.py
strato/tests/test_backend.py
strato/tests/test_cp.py
strato/tests/test_rm.py
strato/tests/test_sync.py
stratocumulus-0.3.0.dist-info/LICENSE
stratocumulus-0.3.0.dist-info/METADATA
stratocumulus-0.3.0.dist-info/WHEEL
stratocumulus-0.3.0.dist-info/entry_points.txt
stratocumulus-0.3.0.dist-info/top_level.txt
stratocumulus-0.3.0.dist-info/RECORD
