Metadata-Version: 2.2
Name: stratocumulus
Version: 0.3.0
Summary: File backend component of Cumulus
Author-email: "Yiming Yang, Joshua Gould, Rimte Rocher, Bo Li" <cumulus-support@googlegroups.com>
License: BSD 3-Clause License
Project-URL: Source, https://github.com/lilab-bcb/stratocumulus
Project-URL: Documentation, https://github.com/lilab-bcb/stratocumulus
Classifier: Development Status :: 5 - Production/Stable
Classifier: Intended Audience :: Developers
Classifier: Intended Audience :: Science/Research
Classifier: License :: OSI Approved :: BSD License
Classifier: Natural Language :: English
Classifier: Operating System :: POSIX :: Linux
Classifier: Operating System :: MacOS :: MacOS X
Classifier: Operating System :: Microsoft :: Windows
Classifier: Programming Language :: Python :: 3
Classifier: Topic :: Software Development :: Build Tools
Requires-Python: >=3
License-File: LICENSE
Requires-Dist: s3fs
Requires-Dist: importlib_metadata>=0.7; python_version < "3.8"
Provides-Extra: test
Requires-Dist: pytest; extra == "test"
